windwoze/__init__.py
windwoze/app.py
windwoze/constants.py
windwoze/input.py
windwoze/shell.py
windwoze/system.py
windwoze/ui.py
windwoze/windows.py
windwoze/word.py
windwoze-0.0.2.dist-info/licenses/LICENSE
windwoze-0.0.2.dist-info/METADATA
windwoze-0.0.2.dist-info/WHEEL
windwoze-0.0.2.dist-info/top_level.txt
windwoze-0.0.2.dist-info/RECORD
