Metadata-Version: 2.4
Name: windwoze
Version: 0.0.2
Summary: AppleTalk but windows
Home-page: 
Author: Annes
Classifier: Programming Language :: Python :: 3
Classifier: Operating System :: OS Independent
Requires-Python: >=3.7
License-File: LICENSE
Dynamic: author
Dynamic: classifier
Dynamic: description
Dynamic: description-content-type
Dynamic: license-file
Dynamic: requires-python
Dynamic: summary
